counter.v
/* obtain from https://medium.com/macoclock/running-verilog-code-on-linux-mac-3b06ddcccc55 */
module counter(out, clk, reset);

  parameter WIDTH = 8;

  output [WIDTH-1 : 0] out;
  input            clk, reset;

  reg [WIDTH-1 : 0]   out;
  wire            clk, reset;

  always @(posedge clk)
    out <= out + 1;

  always @reset
    if (reset)
      assign out = 0;
    else
      deassign out;

endmodule // counter

counter_tb.v
/* obtain from https://medium.com/macoclock/running-verilog-code-on-linux-mac-3b06ddcccc55 */
module test;

  /* Make a reset that pulses once. */
  reg reset = 0;
  initial begin
     $dumpfile("counter.vcd");
     $dumpvars(0,test);

     # 17 reset = 1;
     # 11 reset = 0;
     # 29 reset = 1;
     # 5  reset =0;
     # 513 $finish;
  end

  /* Make a regular pulsing clock. */
  reg clk = 0;
  always #1 clk = !clk;

  wire [7:0] value;
  counter c1 (value, clk, reset);

  initial
     $monitor("At time %t, value = %h (%0d)",
              $time, value, value);
endmodule // test

counter.vcd
$date
	Sun Mar  6 19:55:32 2022
$end
$version
	Icarus Verilog
$end
$timescale
	1s
$end
$scope module test $end
$var wire 8 ! value [7:0] $end
$var reg 1 " clk $end
$var reg 1 # reset $end
$scope module c1 $end
$var wire 1 " clk $end
$var wire 1 # reset $end
$var reg 8 $ out [7:0] $end
$upscope $end
$upscope $end
$enddefinitions $end
#0
$dumpvars
bx $
0#
0"
bx !
$end
#1
1"
#2
0"
#3
1"
#4
0"
#5
1"
#6
0"
#7
1"
#8
0"
#9
1"
#10
0"
#11
1"
#12
0"
#13
1"
#14
0"
#15
1"
#16
0"
#17
b0 !
b0 $
1"
1#
#18
0"
#19
1"
#20
0"
#21
1"
#22
0"
#23
1"
#24
0"
#25
1"
#26
0"
#27
1"
#28
0"
0#
#29
b1 !
b1 $
1"
#30
0"
#31
b10 !
b10 $
1"
#32
0"
#33
b11 !
b11 $
1"
#34
0"
#35
b100 !
b100 $
1"
#36
0"
#37
b101 !
b101 $
1"
#38
0"
#39
b110 !
b110 $
1"
#40
0"
#41
b111 !
b111 $
1"
#42
0"
#43
b1000 !
b1000 $
1"
#44
0"
#45
b1001 !
b1001 $
1"
#46
0"
#47
b1010 !
b1010 $
1"
#48
0"
#49
b1011 !
b1011 $
1"
#50
0"
#51
b1100 !
b1100 $
1"
#52
0"
#53
b1101 !
b1101 $
1"
#54
0"
#55
b1110 !
b1110 $
1"
#56
0"
#57
b0 !
b0 $
1"
1#
#58
0"
#59
1"
#60
0"
#61
1"
#62
0"
0#
#63
b1 !
b1 $
1"
#64
0"
#65
b10 !
b10 $
1"
#66
0"
#67
b11 !
b11 $
1"
#68
0"
#69
b100 !
b100 $
1"
#70
0"
#71
b101 !
b101 $
1"
#72
0"
#73
b110 !
b110 $
1"
#74
0"
#75
b111 !
b111 $
1"
#76
0"
#77
b1000 !
b1000 $
1"
#78
0"
#79
b1001 !
b1001 $
1"
#80
0"
#81
b1010 !
b1010 $
1"
#82
0"
#83
b1011 !
b1011 $
1"
#84
0"
#85
b1100 !
b1100 $
1"
#86
0"
#87
b1101 !
b1101 $
1"
#88
0"
#89
b1110 !
b1110 $
1"
#90
0"
#91
b1111 !
b1111 $
1"
#92
0"
#93
b10000 !
b10000 $
1"
#94
0"
#95
b10001 !
b10001 $
1"
#96
0"
#97
b10010 !
b10010 $
1"
#98
0"
#99
b10011 !
b10011 $
1"
#100
0"
#101
b10100 !
b10100 $
1"
#102
0"
#103
b10101 !
b10101 $
1"
#104
0"
#105
b10110 !
b10110 $
1"
#106
0"
#107
b10111 !
b10111 $
1"
#108
0"
#109
b11000 !
b11000 $
1"
#110
0"
#111
b11001 !
b11001 $
1"
#112
0"
#113
b11010 !
b11010 $
1"
#114
0"
#115
b11011 !
b11011 $
1"
#116
0"
#117
b11100 !
b11100 $
1"
#118
0"
#119
b11101 !
b11101 $
1"
#120
0"
#121
b11110 !
b11110 $
1"
#122
0"
#123
b11111 !
b11111 $
1"
#124
0"
#125
b100000 !
b100000 $
1"
#126
0"
#127
b100001 !
b100001 $
1"
#128
0"
#129
b100010 !
b100010 $
1"
#130
0"
#131
b100011 !
b100011 $
1"
#132
0"
#133
b100100 !
b100100 $
1"
#134
0"
#135
b100101 !
b100101 $
1"
#136
0"
#137
b100110 !
b100110 $
1"
#138
0"
#139
b100111 !
b100111 $
1"
#140
0"
#141
b101000 !
b101000 $
1"
#142
0"
#143
b101001 !
b101001 $
1"
#144
0"
#145
b101010 !
b101010 $
1"
#146
0"
#147
b101011 !
b101011 $
1"
#148
0"
#149
b101100 !
b101100 $
1"
#150
0"
#151
b101101 !
b101101 $
1"
#152
0"
#153
b101110 !
b101110 $
1"
#154
0"
#155
b101111 !
b101111 $
1"
#156
0"
#157
b110000 !
b110000 $
1"
#158
0"
#159
b110001 !
b110001 $
1"
#160
0"
#161
b110010 !
b110010 $
1"
#162
0"
#163
b110011 !
b110011 $
1"
#164
0"
#165
b110100 !
b110100 $
1"
#166
0"
#167
b110101 !
b110101 $
1"
#168
0"
#169
b110110 !
b110110 $
1"
#170
0"
#171
b110111 !
b110111 $
1"
#172
0"
#173
b111000 !
b111000 $
1"
#174
0"
#175
b111001 !
b111001 $
1"
#176
0"
#177
b111010 !
b111010 $
1"
#178
0"
#179
b111011 !
b111011 $
1"
#180
0"
#181
b111100 !
b111100 $
1"
#182
0"
#183
b111101 !
b111101 $
1"
#184
0"
#185
b111110 !
b111110 $
1"
#186
0"
#187
b111111 !
b111111 $
1"
#188
0"
#189
b1000000 !
b1000000 $
1"
#190
0"
#191
b1000001 !
b1000001 $
1"
#192
0"
#193
b1000010 !
b1000010 $
1"
#194
0"
#195
b1000011 !
b1000011 $
1"
#196
0"
#197
b1000100 !
b1000100 $
1"
#198
0"
#199
b1000101 !
b1000101 $
1"
#200
0"
#201
b1000110 !
b1000110 $
1"
#202
0"
#203
b1000111 !
b1000111 $
1"
#204
0"
#205
b1001000 !
b1001000 $
1"
#206
0"
#207
b1001001 !
b1001001 $
1"
#208
0"
#209
b1001010 !
b1001010 $
1"
#210
0"
#211
b1001011 !
b1001011 $
1"
#212
0"
#213
b1001100 !
b1001100 $
1"
#214
0"
#215
b1001101 !
b1001101 $
1"
#216
0"
#217
b1001110 !
b1001110 $
1"
#218
0"
#219
b1001111 !
b1001111 $
1"
#220
0"
#221
b1010000 !
b1010000 $
1"
#222
0"
#223
b1010001 !
b1010001 $
1"
#224
0"
#225
b1010010 !
b1010010 $
1"
#226
0"
#227
b1010011 !
b1010011 $
1"
#228
0"
#229
b1010100 !
b1010100 $
1"
#230
0"
#231
b1010101 !
b1010101 $
1"
#232
0"
#233
b1010110 !
b1010110 $
1"
#234
0"
#235
b1010111 !
b1010111 $
1"
#236
0"
#237
b1011000 !
b1011000 $
1"
#238
0"
#239
b1011001 !
b1011001 $
1"
#240
0"
#241
b1011010 !
b1011010 $
1"
#242
0"
#243
b1011011 !
b1011011 $
1"
#244
0"
#245
b1011100 !
b1011100 $
1"
#246
0"
#247
b1011101 !
b1011101 $
1"
#248
0"
#249
b1011110 !
b1011110 $
1"
#250
0"
#251
b1011111 !
b1011111 $
1"
#252
0"
#253
b1100000 !
b1100000 $
1"
#254
0"
#255
b1100001 !
b1100001 $
1"
#256
0"
#257
b1100010 !
b1100010 $
1"
#258
0"
#259
b1100011 !
b1100011 $
1"
#260
0"
#261
b1100100 !
b1100100 $
1"
#262
0"
#263
b1100101 !
b1100101 $
1"
#264
0"
#265
b1100110 !
b1100110 $
1"
#266
0"
#267
b1100111 !
b1100111 $
1"
#268
0"
#269
b1101000 !
b1101000 $
1"
#270
0"
#271
b1101001 !
b1101001 $
1"
#272
0"
#273
b1101010 !
b1101010 $
1"
#274
0"
#275
b1101011 !
b1101011 $
1"
#276
0"
#277
b1101100 !
b1101100 $
1"
#278
0"
#279
b1101101 !
b1101101 $
1"
#280
0"
#281
b1101110 !
b1101110 $
1"
#282
0"
#283
b1101111 !
b1101111 $
1"
#284
0"
#285
b1110000 !
b1110000 $
1"
#286
0"
#287
b1110001 !
b1110001 $
1"
#288
0"
#289
b1110010 !
b1110010 $
1"
#290
0"
#291
b1110011 !
b1110011 $
1"
#292
0"
#293
b1110100 !
b1110100 $
1"
#294
0"
#295
b1110101 !
b1110101 $
1"
#296
0"
#297
b1110110 !
b1110110 $
1"
#298
0"
#299
b1110111 !
b1110111 $
1"
#300
0"
#301
b1111000 !
b1111000 $
1"
#302
0"
#303
b1111001 !
b1111001 $
1"
#304
0"
#305
b1111010 !
b1111010 $
1"
#306
0"
#307
b1111011 !
b1111011 $
1"
#308
0"
#309
b1111100 !
b1111100 $
1"
#310
0"
#311
b1111101 !
b1111101 $
1"
#312
0"
#313
b1111110 !
b1111110 $
1"
#314
0"
#315
b1111111 !
b1111111 $
1"
#316
0"
#317
b10000000 !
b10000000 $
1"
#318
0"
#319
b10000001 !
b10000001 $
1"
#320
0"
#321
b10000010 !
b10000010 $
1"
#322
0"
#323
b10000011 !
b10000011 $
1"
#324
0"
#325
b10000100 !
b10000100 $
1"
#326
0"
#327
b10000101 !
b10000101 $
1"
#328
0"
#329
b10000110 !
b10000110 $
1"
#330
0"
#331
b10000111 !
b10000111 $
1"
#332
0"
#333
b10001000 !
b10001000 $
1"
#334
0"
#335
b10001001 !
b10001001 $
1"
#336
0"
#337
b10001010 !
b10001010 $
1"
#338
0"
#339
b10001011 !
b10001011 $
1"
#340
0"
#341
b10001100 !
b10001100 $
1"
#342
0"
#343
b10001101 !
b10001101 $
1"
#344
0"
#345
b10001110 !
b10001110 $
1"
#346
0"
#347
b10001111 !
b10001111 $
1"
#348
0"
#349
b10010000 !
b10010000 $
1"
#350
0"
#351
b10010001 !
b10010001 $
1"
#352
0"
#353
b10010010 !
b10010010 $
1"
#354
0"
#355
b10010011 !
b10010011 $
1"
#356
0"
#357
b10010100 !
b10010100 $
1"
#358
0"
#359
b10010101 !
b10010101 $
1"
#360
0"
#361
b10010110 !
b10010110 $
1"
#362
0"
#363
b10010111 !
b10010111 $
1"
#364
0"
#365
b10011000 !
b10011000 $
1"
#366
0"
#367
b10011001 !
b10011001 $
1"
#368
0"
#369
b10011010 !
b10011010 $
1"
#370
0"
#371
b10011011 !
b10011011 $
1"
#372
0"
#373
b10011100 !
b10011100 $
1"
#374
0"
#375
b10011101 !
b10011101 $
1"
#376
0"
#377
b10011110 !
b10011110 $
1"
#378
0"
#379
b10011111 !
b10011111 $
1"
#380
0"
#381
b10100000 !
b10100000 $
1"
#382
0"
#383
b10100001 !
b10100001 $
1"
#384
0"
#385
b10100010 !
b10100010 $
1"
#386
0"
#387
b10100011 !
b10100011 $
1"
#388
0"
#389
b10100100 !
b10100100 $
1"
#390
0"
#391
b10100101 !
b10100101 $
1"
#392
0"
#393
b10100110 !
b10100110 $
1"
#394
0"
#395
b10100111 !
b10100111 $
1"
#396
0"
#397
b10101000 !
b10101000 $
1"
#398
0"
#399
b10101001 !
b10101001 $
1"
#400
0"
#401
b10101010 !
b10101010 $
1"
#402
0"
#403
b10101011 !
b10101011 $
1"
#404
0"
#405
b10101100 !
b10101100 $
1"
#406
0"
#407
b10101101 !
b10101101 $
1"
#408
0"
#409
b10101110 !
b10101110 $
1"
#410
0"
#411
b10101111 !
b10101111 $
1"
#412
0"
#413
b10110000 !
b10110000 $
1"
#414
0"
#415
b10110001 !
b10110001 $
1"
#416
0"
#417
b10110010 !
b10110010 $
1"
#418
0"
#419
b10110011 !
b10110011 $
1"
#420
0"
#421
b10110100 !
b10110100 $
1"
#422
0"
#423
b10110101 !
b10110101 $
1"
#424
0"
#425
b10110110 !
b10110110 $
1"
#426
0"
#427
b10110111 !
b10110111 $
1"
#428
0"
#429
b10111000 !
b10111000 $
1"
#430
0"
#431
b10111001 !
b10111001 $
1"
#432
0"
#433
b10111010 !
b10111010 $
1"
#434
0"
#435
b10111011 !
b10111011 $
1"
#436
0"
#437
b10111100 !
b10111100 $
1"
#438
0"
#439
b10111101 !
b10111101 $
1"
#440
0"
#441
b10111110 !
b10111110 $
1"
#442
0"
#443
b10111111 !
b10111111 $
1"
#444
0"
#445
b11000000 !
b11000000 $
1"
#446
0"
#447
b11000001 !
b11000001 $
1"
#448
0"
#449
b11000010 !
b11000010 $
1"
#450
0"
#451
b11000011 !
b11000011 $
1"
#452
0"
#453
b11000100 !
b11000100 $
1"
#454
0"
#455
b11000101 !
b11000101 $
1"
#456
0"
#457
b11000110 !
b11000110 $
1"
#458
0"
#459
b11000111 !
b11000111 $
1"
#460
0"
#461
b11001000 !
b11001000 $
1"
#462
0"
#463
b11001001 !
b11001001 $
1"
#464
0"
#465
b11001010 !
b11001010 $
1"
#466
0"
#467
b11001011 !
b11001011 $
1"
#468
0"
#469
b11001100 !
b11001100 $
1"
#470
0"
#471
b11001101 !
b11001101 $
1"
#472
0"
#473
b11001110 !
b11001110 $
1"
#474
0"
#475
b11001111 !
b11001111 $
1"
#476
0"
#477
b11010000 !
b11010000 $
1"
#478
0"
#479
b11010001 !
b11010001 $
1"
#480
0"
#481
b11010010 !
b11010010 $
1"
#482
0"
#483
b11010011 !
b11010011 $
1"
#484
0"
#485
b11010100 !
b11010100 $
1"
#486
0"
#487
b11010101 !
b11010101 $
1"
#488
0"
#489
b11010110 !
b11010110 $
1"
#490
0"
#491
b11010111 !
b11010111 $
1"
#492
0"
#493
b11011000 !
b11011000 $
1"
#494
0"
#495
b11011001 !
b11011001 $
1"
#496
0"
#497
b11011010 !
b11011010 $
1"
#498
0"
#499
b11011011 !
b11011011 $
1"
#500
0"
#501
b11011100 !
b11011100 $
1"
#502
0"
#503
b11011101 !
b11011101 $
1"
#504
0"
#505
b11011110 !
b11011110 $
1"
#506
0"
#507
b11011111 !
b11011111 $
1"
#508
0"
#509
b11100000 !
b11100000 $
1"
#510
0"
#511
b11100001 !
b11100001 $
1"
#512
0"
#513
b11100010 !
b11100010 $
1"
#514
0"
#515
b11100011 !
b11100011 $
1"
#516
0"
#517
b11100100 !
b11100100 $
1"
#518
0"
#519
b11100101 !
b11100101 $
1"
#520
0"
#521
b11100110 !
b11100110 $
1"
#522
0"
#523
b11100111 !
b11100111 $
1"
#524
0"
#525
b11101000 !
b11101000 $
1"
#526
0"
#527
b11101001 !
b11101001 $
1"
#528
0"
#529
b11101010 !
b11101010 $
1"
#530
0"
#531
b11101011 !
b11101011 $
1"
#532
0"
#533
b11101100 !
b11101100 $
1"
#534
0"
#535
b11101101 !
b11101101 $
1"
#536
0"
#537
b11101110 !
b11101110 $
1"
#538
0"
#539
b11101111 !
b11101111 $
1"
#540
0"
#541
b11110000 !
b11110000 $
1"
#542
0"
#543
b11110001 !
b11110001 $
1"
#544
0"
#545
b11110010 !
b11110010 $
1"
#546
0"
#547
b11110011 !
b11110011 $
1"
#548
0"
#549
b11110100 !
b11110100 $
1"
#550
0"
#551
b11110101 !
b11110101 $
1"
#552
0"
#553
b11110110 !
b11110110 $
1"
#554
0"
#555
b11110111 !
b11110111 $
1"
#556
0"
#557
b11111000 !
b11111000 $
1"
#558
0"
#559
b11111001 !
b11111001 $
1"
#560
0"
#561
b11111010 !
b11111010 $
1"
#562
0"
#563
b11111011 !
b11111011 $
1"
#564
0"
#565
b11111100 !
b11111100 $
1"
#566
0"
#567
b11111101 !
b11111101 $
1"
#568
0"
#569
b11111110 !
b11111110 $
1"
#570
0"
#571
b11111111 !
b11111111 $
1"
#572
0"
#573
b0 !
b0 $
1"
#574
0"
#575
b1 !
b1 $
1"
